logbeam/__init__.py
logbeam/version.py
logbeam/test/__init__.py
logbeam/test/test_logbeam.py
logbeam-1.0.1.dist-info/DESCRIPTION.rst
logbeam-1.0.1.dist-info/METADATA
logbeam-1.0.1.dist-info/RECORD
logbeam-1.0.1.dist-info/WHEEL
logbeam-1.0.1.dist-info/metadata.json
logbeam-1.0.1.dist-info/top_level.txt
