Metadata-Version: 2.0
Name: logbeam
Version: 1.0.1
Summary: CloudWatch Logs - Python logging handler
Home-page: https://github.com/osperlabs/logbeam
Author: Nicholas Robinson-Wall
Author-email: nick@robinson-wall.com
License: MIT
Platform: UNKNOWN
Classifier: Development Status :: 5 - Production/Stable
Classifier: License :: OSI Approved :: MIT License
Classifier: Intended Audience :: System Administrators
Classifier: Intended Audience :: Developers
Classifier: Programming Language :: Python :: 2
Classifier: Programming Language :: Python :: 3
Classifier: Topic :: System :: Logging
Requires-Dist: awscli-cwlogs (==1.4.0)
Requires-Dist: boto3 (>=1.4.4)
Requires-Dist: six (>=1.10.0)
